setup.py
s3tools/__init__.py
s3tools/s3tools.py
s3tools.egg-info/PKG-INFO
s3tools.egg-info/SOURCES.txt
s3tools.egg-info/dependency_links.txt
s3tools.egg-info/requires.txt
s3tools.egg-info/top_level.txt